__init__.py
catastro_finder.py
local_test.py
catastro_finder-1.4.0.dist-info/METADATA
catastro_finder-1.4.0.dist-info/WHEEL
catastro_finder-1.4.0.dist-info/license.txt
catastro_finder-1.4.0.dist-info/top_level.txt
catastro_finder-1.4.0.dist-info/RECORD
