Metadata-Version: 2.1
Name: catastro-finder
Version: 1.4.0
Summary: Unofficial Catastro Finder. No API keys required
Home-page: https://github.com/jorgeramirezcarrasco/catastro-finder
Author: Jorge Ramírez Carrasco
License: UNKNOWN
Keywords: catastro,web scraping
Platform: UNKNOWN
Requires-Python: >=3.6, <4
Requires-Dist: beautifulsoup4 (>=4.9.3)
Requires-Dist: certifi (>=2020.11.8)
Requires-Dist: chardet (>=3.0.4)
Requires-Dist: idna (>=2.10)
Requires-Dist: requests (>=2.25.0)
Requires-Dist: soupsieve (>=2.0.1)
Requires-Dist: urllib3 (>=1.26.2)
